MANIFEST.in
README
requirements.txt
setup.py
ajenti.plugin.services.egg-info/PKG-INFO
ajenti.plugin.services.egg-info/SOURCES.txt
ajenti.plugin.services.egg-info/dependency_links.txt
ajenti.plugin.services.egg-info/requires.txt
ajenti.plugin.services.egg-info/top_level.txt
ajenti_plugin_services/README.md
ajenti_plugin_services/__init__.py
ajenti_plugin_services/api.py
ajenti_plugin_services/bower.json
ajenti_plugin_services/main.py
ajenti_plugin_services/plugin.yml
ajenti_plugin_services/requirements.txt
ajenti_plugin_services/views.py
ajenti_plugin_services/widget.py
ajenti_plugin_services/locale/app.pot
ajenti_plugin_services/locale/af/LC_MESSAGES/app.js
ajenti_plugin_services/locale/af/LC_MESSAGES/app.po
ajenti_plugin_services/locale/ar/LC_MESSAGES/app.js
ajenti_plugin_services/locale/ar/LC_MESSAGES/app.po
ajenti_plugin_services/locale/be/LC_MESSAGES/app.js
ajenti_plugin_services/locale/be/LC_MESSAGES/app.po
ajenti_plugin_services/locale/bg/LC_MESSAGES/app.js
ajenti_plugin_services/locale/bg/LC_MESSAGES/app.po
ajenti_plugin_services/locale/bn/LC_MESSAGES/app.js
ajenti_plugin_services/locale/bn/LC_MESSAGES/app.po
ajenti_plugin_services/locale/bs/LC_MESSAGES/app.js
ajenti_plugin_services/locale/bs/LC_MESSAGES/app.po
ajenti_plugin_services/locale/ca/LC_MESSAGES/app.js
ajenti_plugin_services/locale/ca/LC_MESSAGES/app.po
ajenti_plugin_services/locale/cs/LC_MESSAGES/app.js
ajenti_plugin_services/locale/cs/LC_MESSAGES/app.po
ajenti_plugin_services/locale/da/LC_MESSAGES/app.js
ajenti_plugin_services/locale/da/LC_MESSAGES/app.po
ajenti_plugin_services/locale/de/LC_MESSAGES/app.js
ajenti_plugin_services/locale/de/LC_MESSAGES/app.po
ajenti_plugin_services/locale/el/LC_MESSAGES/app.js
ajenti_plugin_services/locale/el/LC_MESSAGES/app.po
ajenti_plugin_services/locale/en/LC_MESSAGES/app.po
ajenti_plugin_services/locale/eo/LC_MESSAGES/app.js
ajenti_plugin_services/locale/eo/LC_MESSAGES/app.po
ajenti_plugin_services/locale/es-ES/LC_MESSAGES/app.js
ajenti_plugin_services/locale/es-ES/LC_MESSAGES/app.po
ajenti_plugin_services/locale/et/LC_MESSAGES/app.js
ajenti_plugin_services/locale/et/LC_MESSAGES/app.po
ajenti_plugin_services/locale/fa/LC_MESSAGES/app.js
