Metadata-Version: 1.2
Name: ajenti.plugin.services
Version: 0.33
Summary: Services
Home-page: https://ajenti.org
Author: Ajenti project
Author-email: e@ajenti.org
License: UNKNOWN
Platform: UNKNOWN
Requires-Python: >=3
